README.rst
setup.py
django_treeform/__init__.py
django_treeform.egg-info/PKG-INFO
django_treeform.egg-info/SOURCES.txt
django_treeform.egg-info/dependency_links.txt
django_treeform.egg-info/entry_points.txt
django_treeform.egg-info/not-zip-safe
django_treeform.egg-info/requires.txt
django_treeform.egg-info/top_level.txt
django_treeform/tests/__init__.py
django_treeform/tests/test_it.py