Metadata-Version: 1.1
Name: django-treeform
Version: 0.1
Summary: -
Home-page: https://github.com/podhmo/djang-treeform
Author: podhmo
Author-email: UNKNOWN
License: UNKNOWN
Keywords: django form validation tree
Platform: UNKNOWN
Classifier: Programming Language :: Python
Classifier: Programming Language :: Python :: Implementation :: CPython
